numbyy/__init__.py
numbyy/module.py
numbyy-0.4.0.dist-info/METADATA
numbyy-0.4.0.dist-info/WHEEL
numbyy-0.4.0.dist-info/top_level.txt
numbyy-0.4.0.dist-info/RECORD
