Metadata-Version: 2.4
Name: numbyy
Version: 0.4.0
Summary: Package with sorting algorithms implementation
Home-page: https://github.com/yourusername/my_package
Author: TM
Author-email: moldovskiitimur@gmail.com
Project-URL: Bug Tracker, https://github.com/yourusername/my_package/issues
Classifier: Programming Language :: Python :: 3
Classifier: License :: OSI Approved :: MIT License
Classifier: Operating System :: OS Independent
Requires-Python: >=3.6
Dynamic: author
Dynamic: author-email
Dynamic: classifier
Dynamic: description-content-type
Dynamic: home-page
Dynamic: project-url
Dynamic: requires-python
Dynamic: summary
